{
    "tenantId": "pb.simbal",
    "moduleName": "egov-location",
    "TenantBoundary": [
        {
            "hierarchyType": {
                "code": "REVENUE",
                "name": "REVENUE"
            },
            "boundary": {
                "id": 1,
                "boundaryNum": 1,
                "name": "SIMBAL",
                "localname": "SIMBAL",
                "longitude": null,
                "latitude": null,
                "label": "City",
                "code": "pb.simbal",
                "children": [
                    {
                        "id": 1,
                        "boundaryNum": 1,
                        "name": "SIMBAL",
                        "localname": "SIMBAL",
                        "longitude": null,
                        "latitude": null,
                        "label": "Locality",
                        "code": "WARD1"
                    }
                ]
            }
        },
        {
            "hierarchyType": {
                "code": "ADMIN",
                "name": "ADMIN"
            },
            "boundary": {
                "id": 1,
                "boundaryNum": 1,
                "name": "SIMBAL",
                "localname": "SIMBAL",
                "longitude": null,
                "latitude": null,
                "label": "City",
                "code": "pb.simbal",
                "children": [
                    {
                        "id": 1,
                        "boundaryNum": 1,
                        "name": "SIMBAL",
                        "localname": "SIMBAL",
                        "longitude": null,
                        "latitude": null,
                        "label": "Locality",
                        "code": "WARD1"
                    }
                ]
            }
        }
    ]
}